[ {
  "team_id" : 766,
  "team_name" : "North Carolina Courage",
  "lineup" : [ {
    "player_id" : 3921,
    "player_name" : "Ryan Williams",
    "player_nickname" : null,
    "jersey_number" : 20,
    "country" : {
      "id" : 241,
      "name" : "United States of America"
    }
  }, {
    "player_id" : 4635,
    "player_name" : "Julia Spetsmark",
    "player_nickname" : null,
    "jersey_number" : 16,
    "country" : {
      "id" : 220,
      "name" : "Sweden"
    }
  }, {
    "player_id" : 5041,
    "player_name" : "Cari Roccaro",
    "player_nickname" : null,
    "jersey_number" : 21,
    "country" : {
      "id" : 241,
      "name" : "United States of America"
    }
  }, {
    "player_id" : 5044,
    "player_name" : "Débora Cristiane de Oliveira",
    "player_nickname" : "Debinha",
    "jersey_number" : 10,
    "country" : {
      "id" : 31,
      "name" : "Brazil"
    }
  }, {
    "player_id" : 5047,
    "player_name" : "Jaelene Hinkle",
    "player_nickname" : null,
    "jersey_number" : 15,
    "country" : {
      "id" : 241,
      "name" : "United States of America"
    }
  }, {
    "player_id" : 5048,
    "player_name" : "Katelyn Rowland",
    "player_nickname" : null,
    "jersey_number" : 99,
    "country" : {
      "id" : 241,
      "name" : "United States of America"
    }
  }, {
    "player_id" : 5050,
    "player_name" : "Meredith Speck",
    "player_nickname" : null,
    "jersey_number" : 25,
    "country" : {
      "id" : 241,
      "name" : "United States of America"
    }
  }, {
    "player_id" : 5055,
    "player_name" : "Lynn Williams",
    "player_nickname" : null,
    "jersey_number" : 9,
    "country" : {
      "id" : 241,
      "name" : "United States of America"
    }
  }, {
    "player_id" : 5057,
    "player_name" : "Kaleigh Kurtz",
    "player_nickname" : null,
    "jersey_number" : 3,
    "country" : {
      "id" : 241,
      "name" : "United States of America"
    }
  }, {
    "player_id" : 5080,
    "player_name" : "Kristen Hamilton",
    "player_nickname" : null,
    "jersey_number" : 23,
    "country" : {
      "id" : 241,
      "name" : "United States of America"
    }
  }, {
    "player_id" : 5083,
    "player_name" : "Merritt Mathias",
    "player_nickname" : null,
    "jersey_number" : 11,
    "country" : {
      "id" : 241,
      "name" : "United States of America"
    }
  }, {
    "player_id" : 5084,
    "player_name" : "Denise O\"Sullivan",
    "player_nickname" : "Denise O'Sullivan",
    "jersey_number" : 8,
    "country" : {
      "id" : 109,
      "name" : "Ireland"
    }
  }, {
    "player_id" : 5091,
    "player_name" : "McCall Zerboni",
    "player_nickname" : null,
    "jersey_number" : 7,
    "country" : {
      "id" : 241,
      "name" : "United States of America"
    }
  }, {
    "player_id" : 7181,
    "player_name" : "McKenzie Meehan",
    "player_nickname" : null,
    "jersey_number" : 4,
    "country" : {
      "id" : 241,
      "name" : "United States of America"
    }
  }, {
    "player_id" : 25609,
    "player_name" : "Stephanie Labbe",
    "player_nickname" : null,
    "jersey_number" : 1,
    "country" : {
      "id" : 40,
      "name" : "Canada"
    }
  }, {
    "player_id" : 33350,
    "player_name" : "Leah Pruitt",
    "player_nickname" : null,
    "jersey_number" : 12,
    "country" : {
      "id" : 241,
      "name" : "United States of America"
    }
  }, {
    "player_id" : 33367,
    "player_name" : "Lauren Milliet",
    "player_nickname" : null,
    "jersey_number" : 27,
    "country" : {
      "id" : 241,
      "name" : "United States of America"
    }
  } ]
}, {
  "team_id" : 762,
  "team_name" : "Houston Dash",
  "lineup" : [ {
    "player_id" : 5035,
    "player_name" : "Haley Hanson",
    "player_nickname" : null,
    "jersey_number" : 9,
    "country" : {
      "id" : 241,
      "name" : "United States of America"
    }
  }, {
    "player_id" : 5038,
    "player_name" : "Allysha Chapman",
    "player_nickname" : null,
    "jersey_number" : 4,
    "country" : {
      "id" : 40,
      "name" : "Canada"
    }
  }, {
    "player_id" : 5045,
    "player_name" : "Amber Brooks",
    "player_nickname" : null,
    "jersey_number" : 22,
    "country" : {
      "id" : 241,
      "name" : "United States of America"
    }
  }, {
    "player_id" : 5051,
    "player_name" : "Kealia Ohai",
    "player_nickname" : null,
    "jersey_number" : 7,
    "country" : {
      "id" : 241,
      "name" : "United States of America"
    }
  }, {
    "player_id" : 5056,
    "player_name" : "Jane Campbell",
    "player_nickname" : null,
    "jersey_number" : 1,
    "country" : {
      "id" : 241,
      "name" : "United States of America"
    }
  }, {
    "player_id" : 5059,
    "player_name" : "Kyah Simon",
    "player_nickname" : null,
    "jersey_number" : 17,
    "country" : {
      "id" : 14,
      "name" : "Australia"
    }
  }, {
    "player_id" : 5070,
    "player_name" : "Christine Nairn",
    "player_nickname" : null,
    "jersey_number" : 10,
    "country" : {
      "id" : 241,
      "name" : "United States of America"
    }
  }, {
    "player_id" : 5105,
    "player_name" : "Sofia Huerta",
    "player_nickname" : null,
    "jersey_number" : 11,
    "country" : {
      "id" : 241,
      "name" : "United States of America"
    }
  }, {
    "player_id" : 8382,
    "player_name" : "Clare Polkinghorne",
    "player_nickname" : null,
    "jersey_number" : 5,
    "country" : {
      "id" : 14,
      "name" : "Australia"
    }
  }, {
    "player_id" : 8383,
    "player_name" : "Lindsay Elizabeth Agnew",
    "player_nickname" : "Lindsay Agnew",
    "jersey_number" : 20,
    "country" : {
      "id" : 40,
      "name" : "Canada"
    }
  }, {
    "player_id" : 15180,
    "player_name" : "Sophie Schmidt",
    "player_nickname" : null,
    "jersey_number" : 13,
    "country" : {
      "id" : 40,
      "name" : "Canada"
    }
  }, {
    "player_id" : 15629,
    "player_name" : "Satara Murray",
    "player_nickname" : null,
    "jersey_number" : 44,
    "country" : {
      "id" : 241,
      "name" : "United States of America"
    }
  }, {
    "player_id" : 31934,
    "player_name" : "Cecelia Kizer",
    "player_nickname" : null,
    "jersey_number" : 15,
    "country" : {
      "id" : 241,
      "name" : "United States of America"
    }
  }, {
    "player_id" : 31935,
    "player_name" : "Arianna Jeanette Romero Tellez",
    "player_nickname" : null,
    "jersey_number" : 2,
    "country" : {
      "id" : 147,
      "name" : "Mexico"
    }
  }, {
    "player_id" : 31936,
    "player_name" : "Kristie Mewis",
    "player_nickname" : null,
    "jersey_number" : 19,
    "country" : {
      "id" : 241,
      "name" : "United States of America"
    }
  }, {
    "player_id" : 32019,
    "player_name" : "Cami Privett",
    "player_nickname" : null,
    "jersey_number" : 28,
    "country" : {
      "id" : 241,
      "name" : "United States of America"
    }
  }, {
    "player_id" : 32020,
    "player_name" : "Ariana Catrina Calderón Valdez",
    "player_nickname" : null,
    "jersey_number" : 25,
    "country" : {
      "id" : 147,
      "name" : "Mexico"
    }
  } ]
} ]